tletools/__init__.py
tletools/pandas.py
tletools/tle.py
tletools/utils.py
TLE_tools-0.2.3.dist-info/LICENSE
TLE_tools-0.2.3.dist-info/METADATA
TLE_tools-0.2.3.dist-info/WHEEL
TLE_tools-0.2.3.dist-info/top_level.txt
TLE_tools-0.2.3.dist-info/RECORD
